dougnet/__init__.py
dougnet/metrics.py
dougnet/training.py
dougnet/_computation_graph/__init__.py
dougnet/_computation_graph/_graph_base.py
dougnet/_computation_graph/_modules.py
dougnet/_computation_graph/_node_base.py
dougnet/_computation_graph/_parameter_nodes.py
dougnet/_computation_graph/_computation_nodes/__init__.py
dougnet/_computation_graph/_computation_nodes/_activations.py
dougnet/_computation_graph/_computation_nodes/_batch_norm.py
dougnet/_computation_graph/_computation_nodes/_convolution.py
dougnet/_computation_graph/_computation_nodes/_losses.py
dougnet/_computation_graph/_computation_nodes/_math.py
dougnet/_computation_graph/_computation_nodes/_misc.py
dougnet/_computation_graph/_computation_nodes/_pool.py
dougnet/_computation_graph/_computation_nodes/tests/__init__.py
dougnet/_computation_graph/_computation_nodes/tests/test_batch_norm_1d.py
dougnet/_computation_graph/_computation_nodes/tests/test_batch_norm_2d.py
dougnet/data/__init__.py
dougnet/data/_load_data.py
dougnet/functions/__init__.py
dougnet/functions/_activations.py
dougnet/functions/_convolution.py
dougnet/functions/_embed.py
dougnet/functions/_losses.py
dougnet/functions/_pool.py
dougnet/functions/_batch_norm/__init__.py
dougnet/functions/_batch_norm/_batch_norm_main.py
dougnet/functions/_batch_norm/_batch_norm_multithreaded.py
dougnet/functions/_batch_norm/_batch_norm_singlethreaded.py
dougnet/functions/tests/__init__.py
dougnet/functions/tests/test_batch_norm.py
dougnet/functions/tests/test_convolution.py
dougnet/functions/tests/test_loss.py
dougnet/functions/tests/test_pool.py
dougnet/nograph/_MLP.py
dougnet/nograph/__init__.py
dougnet/optim/__init__.py
dougnet/optim/_optimizers.py
dougnet/optim/tests.py
dougnet/optim/utils.py
dougnet-0.1.8.dist-info/LICENSE.txt
dougnet-0.1.8.dist-info/METADATA
dougnet-0.1.8.dist-info/WHEEL
dougnet-0.1.8.dist-info/top_level.txt
dougnet-0.1.8.dist-info/RECORD
