Metadata-Version: 2.1
Name: dougnet
Version: 0.1.8
Summary: A lightweight, deep learning library written in pure Python for pedagogical purposes.
Home-page: https://github.com/dsrub/DougNet
Author: Douglas Rubin
Author-email: douglas.s.rubin@gmail.com
License: MIT
Classifier: Programming Language :: Python :: 3.8
Classifier: License :: OSI Approved :: MIT License
Classifier: Operating System :: OS Independent
Requires-Python: >=3.8
License-File: LICENSE.txt
Requires-Dist: numpy
Requires-Dist: numba
Requires-Dist: tqdm
